{
  "custodian-guard": {
    "models": 5,
    "prices": {
      "GBP": 42.5,
      "USD": 69,
      "EUR": 55,
      "AUD": 117,
      "CAD": 83
    }
  },
  "allarus-custodians": {
    "models": 3,
    "prices": {
      "GBP": 42.5,
      "USD": 69,
      "EUR": 55,
      "AUD": 117,
      "CAD": 83
    }
  },
  "custodian-wardens": {
    "models": 3,
    "prices": {
      "GBP": 42.5,
      "USD": 69,
      "EUR": 55,
      "AUD": 117,
      "CAD": 83
    }
  },
  "vertus-praetors": {
    "models": 3,
    "prices": {
      "GBP": 52,
      "USD": 85,
      "EUR": 67,
      "AUD": 145,
      "CAD": 100
    }
  },
  "venatari-custodians": {
    "models": 3,
    "prices": {
      "GBP": 42.5,
      "USD": 69,
      "EUR": 55,
      "AUD": 117,
      "CAD": 83
    }
  },
  "blade-champion": {
    "models": 1,
    "prices": {
      "GBP": 26,
      "USD": 42,
      "EUR": 34,
      "AUD": 72,
      "CAD": 53
    }
  },
  "trajann-valoris": {
    "models": 1,
    "prices": {
      "GBP": 35,
      "USD": 60,
      "EUR": 45,
      "AUD": 88,
      "CAD": 70
    }
  },
  "knight-centura": {
    "models": 1,
    "prices": {
      "GBP": 26,
      "USD": 42,
      "EUR": 34,
      "AUD": 72,
      "CAD": 53
    }
  },
  "contemptor-galatus": {
    "models": 1,
    "prices": {
      "GBP": 52,
      "USD": 85,
      "EUR": 67,
      "AUD": 145,
      "CAD": 100
    }
  },
  "contemptor-achillus": {
    "models": 1,
    "prices": {
      "GBP": 52,
      "USD": 85,
      "EUR": 67,
      "AUD": 145,
      "CAD": 100
    }
  }
}
