{
  "faction": "Astra Militarum",
  "units": [
    {
      "id": "armoured_sentinel",
      "name": "Armoured Sentinel",
      "points": 70,
      "models_per_box": 1,
      "box_price": 42.5,
      "prices": {
        "GBP": 42.5,
        "USD": 58.65,
        "EUR": 53.13
      }
    },
    {
      "id": "baneblade",
      "name": "Baneblade",
      "points": 480,
      "models_per_box": 1,
      "box_price": 105,
      "prices": {
        "GBP": 105,
        "USD": 127.99,
        "EUR": 131.25
      }
    },
    {
      "id": "basilisk",
      "name": "Basilisk",
      "points": 135,
      "models_per_box": 1,
      "box_price": 52,
      "prices": {
        "GBP": 52,
        "USD": 65,
        "EUR": 65
      }
    },
    {
      "id": "cadian_shock_troops",
      "name": "Cadian Shock Troops",
      "points": 60,
      "models_per_box": 10,
      "box_price": 31.5,
      "prices": {
        "GBP": 31.5,
        "USD": 45.05,
        "EUR": 39.38
      }
    },
    {
      "id": "castellan",
      "name": "Castellan",
      "points": 75,
      "models_per_box": 1,
      "box_price": 26,
      "prices": {
        "GBP": 26,
        "USD": 33.15,
        "EUR": 32.5
      }
    },
    {
      "id": "catachan_jungle_fighters",
      "name": "Catachan Jungle Fighters",
      "points": 55,
      "models_per_box": 10,
      "box_price": 31.5,
      "prices": {
        "GBP": 31.5,
        "USD": 35,
        "EUR": 39.38
      }
    },
    {
      "id": "commissar",
      "name": "Commissar",
      "points": 30,
      "models_per_box": 1,
      "box_price": 26,
      "prices": {
        "GBP": 26,
        "USD": 33.15,
        "EUR": 32.5
      }
    },
    {
      "id": "death_korps_of_krieg",
      "name": "Death Korps of Krieg",
      "points": 65,
      "models_per_box": 10,
      "box_price": 35,
      "prices": {
        "GBP": 35,
        "USD": 45,
        "EUR": 43.75
      }
    },
    {
      "id": "field_ordnance_battery",
      "name": "Field Ordnance Battery",
      "points": 120,
      "models_per_box": 2,
      "box_price": 42.5,
      "prices": {
        "GBP": 42.5,
        "USD": 51,
        "EUR": 53.13
      }
    },
    {
      "id": "mortar_team",
      "name": "Heavy Weapons Squad",
      "points": 60,
      "models_per_box": 3,
      "box_price": 28,
      "prices": {
        "GBP": 28,
        "USD": 29.99,
        "EUR": 35
      }
    },
    {
      "id": "hellhound",
      "name": "Hellhound",
      "points": 125,
      "models_per_box": 1,
      "box_price": 47.5,
      "prices": {
        "GBP": 47.5,
        "USD": 58.19,
        "EUR": 59.38
      }
    },
    {
      "id": "hydra",
      "name": "Hydra",
      "points": 110,
      "models_per_box": 1,
      "box_price": 47.5,
      "prices": {
        "GBP": 47.5,
        "USD": 58.65,
        "EUR": 59.38
      }
    },
    {
      "id": "infantry_squad",
      "name": "Infantry Squad",
      "points": 60,
      "models_per_box": 10,
      "box_price": 31.5,
      "prices": {
        "GBP": 31.5,
        "USD": 45.05,
        "EUR": 39.38
      }
    },
    {
      "id": "battle_tank",
      "name": "Leman Russ Battle Tank",
      "points": 195,
      "models_per_box": 1,
      "box_price": 52,
      "prices": {
        "GBP": 52,
        "USD": 65,
        "EUR": 65
      }
    },
    {
      "id": "demolisher",
      "name": "Leman Russ Demolisher",
      "points": 200,
      "models_per_box": 1,
      "box_price": 52,
      "prices": {
        "GBP": 52,
        "USD": 65,
        "EUR": 65
      }
    },
    {
      "id": "lord_solar_leontus",
      "name": "Lord Solar Leontus",
      "points": 125,
      "models_per_box": 1,
      "box_price": 42.5,
      "prices": {
        "GBP": 42.5,
        "USD": 55.25,
        "EUR": 53.13
      }
    },
    {
      "id": "manticore",
      "name": "Manticore",
      "points": 150,
      "models_per_box": 1,
      "box_price": 52,
      "prices": {
        "GBP": 52,
        "USD": 65.5,
        "EUR": 65
      }
    },
    {
      "id": "medusa",
      "name": "Medusa",
      "points": 130,
      "models_per_box": 1,
      "box_price": 47.5,
      "prices": {
        "GBP": 47.5,
        "USD": 58.65,
        "EUR": 59.38
      }
    },
    {
      "id": "ogryn",
      "name": "Ogryn Squad",
      "points": 130,
      "models_per_box": 3,
      "box_price": 35,
      "prices": {
        "GBP": 35,
        "USD": 45.05,
        "EUR": 43.75
      }
    },
    {
      "id": "ratling",
      "name": "Ratlings",
      "points": 60,
      "models_per_box": 5,
      "box_price": 26,
      "prices": {
        "GBP": 26,
        "USD": 33.5,
        "EUR": 32.5
      }
    },
    {
      "id": "rogue_trader",
      "name": "Rogue Trader",
      "points": 50,
      "models_per_box": 1,
      "box_price": 26,
      "prices": {
        "GBP": 26,
        "USD": 31.96,
        "EUR": 32.5
      }
    },
    {
      "id": "rough_riders",
      "name": "Rough Riders",
      "points": 75,
      "models_per_box": 5,
      "box_price": 35,
      "prices": {
        "GBP": 35,
        "USD": 46.99,
        "EUR": 43.75
      }
    },
    {
      "id": "scout_sentinel",
      "name": "Scout Sentinel",
      "points": 60,
      "models_per_box": 1,
      "box_price": 42.5,
      "prices": {
        "GBP": 42.5,
        "USD": 46.99,
        "EUR": 53.13
      }
    },
    {
      "id": "sergeant_hatt",
      "name": "Sergeant Harker",
      "points": 55,
      "models_per_box": 1,
      "box_price": 26,
      "prices": {
        "GBP": 26,
        "USD": 29.99,
        "EUR": 32.5
      }
    },
    {
      "id": "tank_commander",
      "name": "Tank Commander",
      "points": 205,
      "models_per_box": 1,
      "box_price": 52,
      "prices": {
        "GBP": 52,
        "USD": 65,
        "EUR": 65
      }
    },
    {
      "id": "tempestus_scions",
      "name": "Tempestus Scions",
      "points": 55,
      "models_per_box": 5,
      "box_price": 28,
      "prices": {
        "GBP": 28,
        "USD": 33.99,
        "EUR": 35
      }
    },
    {
      "id": "valkyrie",
      "name": "Valkyrie",
      "points": 170,
      "models_per_box": 1,
      "box_price": 58,
      "prices": {
        "GBP": 58,
        "USD": 75,
        "EUR": 72.5
      }
    },
    {
      "id": "wyvern",
      "name": "Wyvern",
      "points": 110,
      "models_per_box": 1,
      "box_price": 47.5,
      "prices": {
        "GBP": 47.5,
        "USD": 58.65,
        "EUR": 59.38
      }
    }
  ]
}